scrava/__init__.py
scrava/bot.py
scrava/logging.py
scrava/py.typed
scrava/utils.py
scrava-0.1.1.dist-info/licenses/LICENSE
scrava-0.1.1.dist-info/METADATA
scrava-0.1.1.dist-info/WHEEL
scrava-0.1.1.dist-info/entry_points.txt
scrava-0.1.1.dist-info/top_level.txt
scrava-0.1.1.dist-info/RECORD
