Metadata-Version: 2.4
Name: scrava
Version: 0.1.1
Summary: The Definitive Web Scraping Framework for Python
Author-email: Nextract Data Solutions <hello@nextract.dev>, Parth Ravrani <hello@nextract.dev>
Maintainer-email: Nextract Data Solutions <hello@nextract.dev>
License: MIT
Project-URL: Homepage, https://github.com/nextractdevelopers/Scrava
Project-URL: Documentation, https://github.com/nextractdevelopers/Scrava#readme
Project-URL: Repository, https://github.com/nextractdevelopers/Scrava
Project-URL: Issues, https://github.com/nextractdevelopers/Scrava/issues
Project-URL: Changelog, https://github.com/nextractdevelopers/Scrava/releases
Project-URL: Company, https://nextract.dev
Keywords: web-scraping,scraping,crawler,spider,async,asyncio,http,playwright,data-extraction,web-automation
Classifier: Development Status :: 4 - Beta
Classifier: Intended Audience :: Developers
Classifier: License :: OSI Approved :: MIT License
Classifier: Programming Language :: Python :: 3
Classifier: Programming Language :: Python :: 3.8
Classifier: Programming Language :: Python :: 3.9
Classifier: Programming Language :: Python :: 3.10
Classifier: Programming Language :: Python :: 3.11
Classifier: Programming Language :: Python :: 3.12
Classifier: Programming Language :: Python :: 3.13
Classifier: Topic :: Software Development :: Libraries :: Python Modules
Classifier: Topic :: Internet :: WWW/HTTP
Classifier: Framework :: AsyncIO
Requires-Python: >=3.8
License-File: LICENSE
Requires-Dist: httpx>=0.27.0
Requires-Dist: parsel>=1.8.1
Requires-Dist: pydantic>=2.0.0
Requires-Dist: pydantic-settings>=2.0.0
Requires-Dist: PyYAML>=6.0
Requires-Dist: structlog>=24.0.0
Requires-Dist: typer>=0.12.0
Requires-Dist: rich>=13.0.0
Provides-Extra: browser
Requires-Dist: playwright>=1.40.0; extra == "browser"
Provides-Extra: redis
Requires-Dist: redis>=5.0.0; extra == "redis"
Requires-Dist: redis-py-cluster>=2.1.0; extra == "redis"
Provides-Extra: mongo
Requires-Dist: motor>=3.3.0; extra == "mongo"
Provides-Extra: excel
Requires-Dist: openpyxl>=3.1.0; extra == "excel"
Provides-Extra: all
Requires-Dist: playwright>=1.40.0; extra == "all"
Requires-Dist: redis>=5.0.0; extra == "all"
Requires-Dist: motor>=3.3.0; extra == "all"
Requires-Dist: openpyxl>=3.1.0; extra == "all"
Provides-Extra: dev
Requires-Dist: pytest>=7.0.0; extra == "dev"
Requires-Dist: pytest-asyncio>=0.21.0; extra == "dev"
Requires-Dist: black>=23.0.0; extra == "dev"
Requires-Dist: isort>=5.12.0; extra == "dev"
Requires-Dist: mypy>=1.0.0; extra == "dev"
Dynamic: license-file
